hypersphere_ml/__init__.py
hypersphere_ml/hypersphere.py
hypersphere_ml-0.0.1.dist-info/licenses/LICENSE
hypersphere_ml-0.0.1.dist-info/METADATA
hypersphere_ml-0.0.1.dist-info/WHEEL
hypersphere_ml-0.0.1.dist-info/top_level.txt
hypersphere_ml-0.0.1.dist-info/RECORD
