Metadata-Version: 2.4
Name: hypersphere-ml
Version: 0.0.1
Summary: Minimal enclosing hypersphere for n-dimensional datasets
Author-email: Nilanjan Panda <npanda@iitb.ac.in>
Project-URL: Homepage, https://github.com/yourname/hypersphere-ml
Requires-Python: >=3.9
License-File: LICENSE
Requires-Dist: numpy
Requires-Dist: pandas
Requires-Dist: matplotlib
Requires-Dist: scikit-learn
Dynamic: license-file
